[
{"type":"header","version":"5.1.1deb5ubuntu1","comment":"Export to JSON plugin for PHPMyAdmin"},
{"type":"database","name":"nftsns"},
{"type":"table","name":"event","database":"nftsns","data":
[
{"id":"1","user_id":"2","title":"Downtown Holiday Art Market","description":"Find unique, handmade gifts for the holidays! Over 50 local artists selling paintings, pottery, jewelry, and textiles.","kind":"Art Fair","event_date":"2025-12-05","status":"2","status_message":"Event Approved and Live","join_start":"2025-10-15","join_end":"2025-11-20","exposure_pre_start":"2025-11-01","exposure_pre_end":"2025-11-15","exposure_main_start":"2025-11-16","exposure_main_end":"2025-12-05","createdat":"2025-11-16 06:49:28","updatedat":"2025-11-16 11:47:02","join_start_ts":null,"join_end_ts":null,"exposure_pre_start_ts":null,"exposure_pre_end_ts":null,"exposure_main_start_ts":null,"exposure_main_end_ts":null},
{"id":"2","user_id":"7","title":"CityVoice Singing Competition 2026","description":"Do you have the best voice in the city? Audition for a chance to win $5,000 and a record deal. All genres welcome.","kind":"Competition","event_date":"2026-02-15","status":"0","status_message":"Awaiting admin approval","join_start":"2025-12-01","join_end":"2026-01-31","exposure_pre_start":"2025-11-20","exposure_pre_end":"2025-11-30","exposure_main_start":"2025-12-01","exposure_main_end":"2026-02-15","createdat":"2025-11-16 06:49:28","updatedat":"0000-00-00 00:00:00","join_start_ts":null,"join_end_ts":null,"exposure_pre_start_ts":null,"exposure_pre_end_ts":null,"exposure_main_start_ts":null,"exposure_main_end_ts":null},
{"id":"3","user_id":"3","title":"SynthWave Headphone Launch Party","description":"Experience the new S-1000 headphones. Live DJ, product demos, and exclusive launch-day discounts.","kind":"Product Promotion","event_date":"2025-10-20","status":"2","status_message":"Event Completed","join_start":null,"join_end":null,"exposure_pre_start":"2025-09-15","exposure_pre_end":"2025-09-30","exposure_main_start":"2025-10-01","exposure_main_end":"2025-10-20","createdat":"2025-11-16 06:49:28","updatedat":"0000-00-00 00:00:00","join_start_ts":null,"join_end_ts":null,"exposure_pre_start_ts":null,"exposure_pre_end_ts":null,"exposure_main_start_ts":null,"exposure_main_end_ts":null},
{"id":"4","user_id":"11","title":"Zenith Yoga Studio - Free Open House","description":"Try any class for free all day! Meet our instructors and get 20% off all new memberships signed on this day.","kind":"Service Promotion","event_date":"2025-11-23","status":"1","status_message":"Live","join_start":null,"join_end":null,"exposure_pre_start":"2025-11-01","exposure_pre_end":"2025-11-10","exposure_main_start":"2025-11-11","exposure_main_end":"2025-11-23","createdat":"2025-11-16 06:49:28","updatedat":"0000-00-00 00:00:00","join_start_ts":null,"join_end_ts":null,"exposure_pre_start_ts":null,"exposure_pre_end_ts":null,"exposure_main_start_ts":null,"exposure_main_end_ts":null},
{"id":"5","user_id":"14","title":"Annual Downtown Chili Cook-Off","description":"This event has been cancelled due to unexpected venue issues. All entry fees will be refunded.","kind":"Competition","event_date":"2025-11-30","status":"3","status_message":"Cancelled - Venue Unavailable","join_start":"2025-10-01","join_end":"2025-11-15","exposure_pre_start":"2025-10-01","exposure_pre_end":"2025-10-15","exposure_main_start":"2025-10-16","exposure_main_end":"2025-11-15","createdat":"2025-11-16 06:49:28","updatedat":"0000-00-00 00:00:00","join_start_ts":null,"join_end_ts":null,"exposure_pre_start_ts":null,"exposure_pre_end_ts":null,"exposure_main_start_ts":null,"exposure_main_end_ts":null},
{"id":"6","user_id":"5","title":"CodeQuick: Free Intro to Python Workshop","description":"Learn the basics of Python in this 2-hour introductory workshop. No experience required. Laptops provided.","kind":"Service Promotion","event_date":"2026-01-10","status":"0","status_message":"Awaiting admin approval","join_start":"2025-11-20","join_end":"2026-01-08","exposure_pre_start":"2025-11-15","exposure_pre_end":"2025-11-19","exposure_main_start":"2025-11-20","exposure_main_end":"2026-01-10","createdat":"2025-11-16 06:49:28","updatedat":"0000-00-00 00:00:00","join_start_ts":null,"join_end_ts":null,"exposure_pre_start_ts":null,"exposure_pre_end_ts":null,"exposure_main_start_ts":null,"exposure_main_end_ts":null},
{"id":"7","user_id":"8","title":"The Corner Bakery: Holiday Pop-up Sale","description":"Pre-order your holiday pies, cookies, and specialty breads. Featuring our famous gingerbread and stollen.","kind":"Product Promotion","event_date":"2025-12-18","status":"1","status_message":"Live - Accepting Pre-orders","join_start":null,"join_end":null,"exposure_pre_start":"2025-11-10","exposure_pre_end":"2025-11-17","exposure_main_start":"2025-11-18","exposure_main_end":"2025-12-17","createdat":"2025-11-16 06:49:28","updatedat":"0000-00-00 00:00:00","join_start_ts":null,"join_end_ts":null,"exposure_pre_start_ts":null,"exposure_pre_end_ts":null,"exposure_main_start_ts":null,"exposure_main_end_ts":null},
{"id":"8","user_id":"1","title":"Summer Nights Art Fair","description":"Our annual summer art fair, featuring live music, food trucks, and over 100 artisans.","kind":"Art Fair","event_date":"2025-08-15","status":"2","status_message":"Event Completed","join_start":"2025-05-01","join_end":"2025-06-15","exposure_pre_start":"2025-06-20","exposure_pre_end":"2025-06-30","exposure_main_start":"2025-07-01","exposure_main_end":"2025-08-15","createdat":"2025-11-16 06:49:28","updatedat":"0000-00-00 00:00:00","join_start_ts":null,"join_end_ts":null,"exposure_pre_start_ts":null,"exposure_pre_end_ts":null,"exposure_main_start_ts":null,"exposure_main_end_ts":null},
{"id":"9","user_id":"19","title":"48-Hour Indie Game Dev Jam","description":"Can you build a game in a weekend? Join alone or with a team. Theme announced at the start!","kind":"Competition","event_date":"2025-11-29","status":"1","status_message":"Registration Open","join_start":"2025-11-01","join_end":"2025-11-28","exposure_pre_start":"2025-10-25","exposure_pre_end":"2025-10-31","exposure_main_start":"2025-11-01","exposure_main_end":"2025-11-29","createdat":"2025-11-16 06:49:28","updatedat":"0000-00-00 00:00:00","join_start_ts":null,"join_end_ts":null,"exposure_pre_start_ts":null,"exposure_pre_end_ts":null,"exposure_main_start_ts":null,"exposure_main_end_ts":null},
{"id":"10","user_id":"6","title":"Community 5K Turkey Trot","description":"A fun 5K run\/walk to support the local food bank. All participants get a t-shirt and medal.","kind":"Charity Event","event_date":"2025-11-22","status":"1","status_message":"Live","join_start":"2025-09-15","join_end":"2025-11-20","exposure_pre_start":"2025-09-10","exposure_pre_end":"2025-09-14","exposure_main_start":"2025-09-15","exposure_main_end":"2025-11-22","createdat":"2025-11-16 06:49:28","updatedat":"0000-00-00 00:00:00","join_start_ts":null,"join_end_ts":null,"exposure_pre_start_ts":null,"exposure_pre_end_ts":null,"exposure_main_start_ts":null,"exposure_main_end_ts":null},
{"id":"11","user_id":"12","title":"Spring 2026 Fashion Line Preview","description":"Exclusive preview of our new Spring 2026 collection. Invite only.","kind":"Product Promotion","event_date":"2026-03-01","status":"0","status_message":"Draft","join_start":null,"join_end":null,"exposure_pre_start":null,"exposure_pre_end":null,"exposure_main_start":null,"exposure_main_end":null,"createdat":"2025-11-16 06:49:28","updatedat":"0000-00-00 00:00:00","join_start_ts":null,"join_end_ts":null,"exposure_pre_start_ts":null,"exposure_pre_end_ts":null,"exposure_main_start_ts":null,"exposure_main_end_ts":null},
{"id":"12","user_id":"15","title":"Digital Marketing 101 Seminar","description":"Learn SEO, SEM, and Social Media strategy from industry experts. Completed event.","kind":"Service Promotion","event_date":"2025-09-05","status":"2","status_message":"Event Completed","join_start":"2025-07-15","join_end":"2025-09-01","exposure_pre_start":"2025-07-01","exposure_pre_end":"2025-07-14","exposure_main_start":"2025-07-15","exposure_main_end":"2025-09-05","createdat":"2025-11-16 06:49:28","updatedat":"0000-00-00 00:00:00","join_start_ts":null,"join_end_ts":null,"exposure_pre_start_ts":null,"exposure_pre_end_ts":null,"exposure_main_start_ts":null,"exposure_main_end_ts":null},
{"id":"13","user_id":"4","title":"Riverside Graffiti & Street Art Expo","description":"Live graffiti battles, blackbook showcases, and street art installations. Seeking artists to participate.","kind":"Art Fair","event_date":"2026-04-10","status":"0","status_message":"Pending Artist Submissions","join_start":"2025-12-01","join_end":"2026-03-15","exposure_pre_start":"2025-11-15","exposure_pre_end":"2025-11-30","exposure_main_start":"2025-12-01","exposure_main_end":"2026-04-10","createdat":"2025-11-16 06:49:28","updatedat":"0000-00-00 00:00:00","join_start_ts":null,"join_end_ts":null,"exposure_pre_start_ts":null,"exposure_pre_end_ts":null,"exposure_main_start_ts":null,"exposure_main_end_ts":null},
{"id":"14","user_id":"17","title":"Local Landscapes Photography Contest","description":"Submit your best photos of our city and surrounding nature. Winners featured in City Hall.","kind":"Competition","event_date":"2025-10-01","status":"2","status_message":"Judging Complete - Winners Announced","join_start":"2025-08-01","join_end":"2025-09-15","exposure_pre_start":"2025-07-20","exposure_pre_end":"2025-07-31","exposure_main_start":"2025-08-01","exposure_main_end":"2025-09-15","createdat":"2025-11-16 06:49:28","updatedat":"0000-00-00 00:00:00","join_start_ts":null,"join_end_ts":null,"exposure_pre_start_ts":null,"exposure_pre_end_ts":null,"exposure_main_start_ts":null,"exposure_main_end_ts":null},
{"id":"15","user_id":"9","title":"WebDev Bootcamp - Info Session","description":"Learn about our full-stack developer bootcamp. Find out about curriculum, financing, and career services.","kind":"Service Promotion","event_date":"2025-11-19","status":"1","status_message":"Live - RSVP Open","join_start":"2025-11-01","join_end":"2025-11-19","exposure_pre_start":"2025-10-25","exposure_pre_end":"2025-10-31","exposure_main_start":"2025-11-01","exposure_main_end":"2025-11-19","createdat":"2025-11-16 06:49:28","updatedat":"0000-00-00 00:00:00","join_start_ts":null,"join_end_ts":null,"exposure_pre_start_ts":null,"exposure_pre_end_ts":null,"exposure_main_start_ts":null,"exposure_main_end_ts":null},
{"id":"16","user_id":"13","title":"TechDealz Black Friday Super Sale","description":"Massive discounts on laptops, TVs, gaming consoles, and smart home devices. Doors open 5 AM.","kind":"Product Promotion","event_date":"2025-11-28","status":"1","status_message":"Event Approved and Live","join_start":null,"join_end":null,"exposure_pre_start":"2025-11-10","exposure_pre_end":"2025-11-20","exposure_main_start":"2025-11-21","exposure_main_end":"2025-11-28","createdat":"2025-11-16 06:49:28","updatedat":"0000-00-00 00:00:00","join_start_ts":null,"join_end_ts":null,"exposure_pre_start_ts":null,"exposure_pre_end_ts":null,"exposure_main_start_ts":null,"exposure_main_end_ts":null},
{"id":"17","user_id":"18","title":"University Student Art Show","description":"End-of-semester show for the Fine Arts department. Open to the public.","kind":"Art Fair","event_date":"2025-12-01","status":"1","status_message":"Live","join_start":null,"join_end":null,"exposure_pre_start":"2025-11-15","exposure_pre_end":"2025-11-20","exposure_main_start":"2025-11-21","exposure_main_end":"2025-12-03","createdat":"2025-11-16 06:49:28","updatedat":"0000-00-00 00:00:00","join_start_ts":null,"join_end_ts":null,"exposure_pre_start_ts":null,"exposure_pre_end_ts":null,"exposure_main_start_ts":null,"exposure_main_end_ts":null},
{"id":"18","user_id":"20","title":"Battle of the Bands 2026","description":"Local bands compete for studio time and the main stage slot at the Summerfest. Applications open soon.","kind":"Competition","event_date":"2026-01-25","status":"0","status_message":"Awaiting approval","join_start":"2025-11-25","join_end":"2026-01-10","exposure_pre_start":"2025-11-18","exposure_pre_end":"2025-11-24","exposure_main_start":"2025-11-25","exposure_main_end":"2026-01-25","createdat":"2025-11-16 06:49:28","updatedat":"0000-00-00 00:00:00","join_start_ts":null,"join_end_ts":null,"exposure_pre_start_ts":null,"exposure_pre_end_ts":null,"exposure_main_start_ts":null,"exposure_main_end_ts":null},
{"id":"19","user_id":"10","title":"Guided Historical City Tour (Nov 10)","description":"This tour was cancelled due to poor weather conditions.","kind":"Service Promotion","event_date":"2025-11-10","status":"3","status_message":"Cancelled - Weather","join_start":"2025-10-15","join_end":"2025-11-09","exposure_pre_start":"2025-10-10","exposure_pre_end":"2025-10-14","exposure_main_start":"2025-10-15","exposure_main_end":"2025-11-10","createdat":"2025-11-16 06:49:28","updatedat":"0000-00-00 00:00:00","join_start_ts":null,"join_end_ts":null,"exposure_pre_start_ts":null,"exposure_pre_end_ts":null,"exposure_main_start_ts":null,"exposure_main_end_ts":null},
{"id":"20","user_id":"16","title":"\"GamerFuel\" Energy Drink Free Tasting","description":"Try our three new flavors (Citrus-Rage, Blue-Shock, Cherry-Core) at the Central Mall.","kind":"Product Promotion","event_date":"2025-11-25","status":"1","status_message":"Live","join_start":null,"join_end":null,"exposure_pre_start":"2025-11-15","exposure_pre_end":"2025-11-19","exposure_main_start":"2025-11-20","exposure_main_end":"2025-11-25","createdat":"2025-11-16 06:49:28","updatedat":"0000-00-00 00:00:00","join_start_ts":null,"join_end_ts":null,"exposure_pre_start_ts":null,"exposure_pre_end_ts":null,"exposure_main_start_ts":null,"exposure_main_end_ts":null},
{"id":"21","user_id":"2","title":"Black Friday 2025 Super Sale","description":"Coordinated campaign across Instagram, Facebook, and Email. 20+ posts, 10 stories, 5 video ads. Goal: 30% revenue increase.","kind":"Product Promotion","event_date":"2025-11-28","status":"1","status_message":"Teaser phase live","join_start":null,"join_end":null,"exposure_pre_start":"2025-11-15","exposure_pre_end":"2025-11-19","exposure_main_start":"2025-11-20","exposure_main_end":"2025-11-28","createdat":"2025-11-16 06:49:28","updatedat":"0000-00-00 00:00:00","join_start_ts":null,"join_end_ts":null,"exposure_pre_start_ts":null,"exposure_pre_end_ts":null,"exposure_main_start_ts":null,"exposure_main_end_ts":null},
{"id":"22","user_id":"7","title":"Cyber Monday Flash Deals","description":"TikTok and Instagram Reels campaign. Hourly flash deals promoted via stories and influencer partnerships.","kind":"SNS Campaign","event_date":"2025-12-01","status":"0","status_message":"Pending - Awaiting creative assets","join_start":null,"join_end":null,"exposure_pre_start":"2025-11-25","exposure_pre_end":"2025-11-30","exposure_main_start":"2025-12-01","exposure_main_end":"2025-12-01","createdat":"2025-11-16 06:49:28","updatedat":"0000-00-00 00:00:00","join_start_ts":null,"join_end_ts":null,"exposure_pre_start_ts":null,"exposure_pre_end_ts":null,"exposure_main_start_ts":null,"exposure_main_end_ts":null},
{"id":"23","user_id":"3","title":"Spooky Savings Halloween Promo","description":"Completed Halloween-themed email and social media campaign. Featured user-generated content (costumes).","kind":"Product Promotion","event_date":"2025-10-31","status":"2","status_message":"Campaign Completed","join_start":null,"join_end":null,"exposure_pre_start":"2025-10-15","exposure_pre_end":"2025-10-19","exposure_main_start":"2025-10-20","exposure_main_end":"2025-10-31","createdat":"2025-11-16 06:49:28","updatedat":"0000-00-00 00:00:00","join_start_ts":null,"join_end_ts":null,"exposure_pre_start_ts":null,"exposure_pre_end_ts":null,"exposure_main_start_ts":null,"exposure_main_end_ts":null},
{"id":"24","user_id":"11","title":"12 Days of Giveaways (Holiday 2025)","description":"Daily giveaway event on Instagram. Users must follow, like, and tag friends to enter each day.","kind":"Giveaway","event_date":"2025-12-24","status":"0","status_message":"Pending - Finalizing brand partners","join_start":"2025-12-13","join_end":"2025-12-24","exposure_pre_start":"2025-12-01","exposure_pre_end":"2025-12-12","exposure_main_start":"2025-12-13","exposure_main_end":"2025-12-24","createdat":"2025-11-16 06:49:28","updatedat":"0000-00-00 00:00:00","join_start_ts":null,"join_end_ts":null,"exposure_pre_start_ts":null,"exposure_pre_end_ts":null,"exposure_main_start_ts":null,"exposure_main_end_ts":null},
{"id":"25","user_id":"14","title":"\"New Year, New You\" Fitness Challenge","description":"Service promotion for gym memberships. 6-week challenge. Social posts, email nurture sequence, and 3 webinars.","kind":"Service Promotion","event_date":"2026-01-31","status":"1","status_message":"Early-bird sign-ups are live","join_start":"2025-11-15","join_end":"2026-01-10","exposure_pre_start":"2025-11-15","exposure_pre_end":"2025-12-19","exposure_main_start":"2025-12-20","exposure_main_end":"2026-01-31","createdat":"2025-11-16 06:49:28","updatedat":"0000-00-00 00:00:00","join_start_ts":null,"join_end_ts":null,"exposure_pre_start_ts":null,"exposure_pre_end_ts":null,"exposure_main_start_ts":null,"exposure_main_end_ts":null},
{"id":"26","user_id":"5","title":"@StyleMaven x Aura Perfume Collab","description":"Influencer collaboration. 3 feed posts, 8 stories, and 1 YouTube video. Ended Nov 10.","kind":"Influencer Collab","event_date":"2025-11-10","status":"2","status_message":"Campaign Completed","join_start":null,"join_end":null,"exposure_pre_start":"2025-10-28","exposure_pre_end":"2025-10-31","exposure_main_start":"2025-11-01","exposure_main_end":"2025-11-10","createdat":"2025-11-16 06:49:28","updatedat":"0000-00-00 00:00:00","join_start_ts":null,"join_end_ts":null,"exposure_pre_start_ts":null,"exposure_pre_end_ts":null,"exposure_main_start_ts":null,"exposure_main_end_ts":null},
{"id":"27","user_id":"8","title":"\"Winter Glow\" Skincare Line Launch","description":"New product launch. Teaser campaign involves \"What's coming?\" posts. Main launch includes tutorials and reviews.","kind":"Product Promotion","event_date":"2025-12-15","status":"0","status_message":"Pending Launch","join_start":null,"join_end":null,"exposure_pre_start":"2025-11-20","exposure_pre_end":"2025-11-30","exposure_main_start":"2025-12-01","exposure_main_end":"2025-12-15","createdat":"2025-11-16 06:49:28","updatedat":"0000-00-00 00:00:00","join_start_ts":null,"join_end_ts":null,"exposure_pre_start_ts":null,"exposure_pre_end_ts":null,"exposure_main_start_ts":null,"exposure_main_end_ts":null},
{"id":"28","user_id":"1","title":"TaskMaster 2.0 App Launch","description":"Promoting new app features. Campaign includes \"before & after\" comparison videos and a 20% off-promo code.","kind":"Service Promotion","event_date":"2025-11-24","status":"1","status_message":"Main campaign is live","join_start":null,"join_end":null,"exposure_pre_start":"2025-11-01","exposure_pre_end":"2025-11-09","exposure_main_start":"2025-11-10","exposure_main_end":"2025-11-24","createdat":"2025-11-16 06:49:28","updatedat":"0000-00-00 00:00:00","join_start_ts":null,"join_end_ts":null,"exposure_pre_start_ts":null,"exposure_pre_end_ts":null,"exposure_main_start_ts":null,"exposure_main_end_ts":null},
{"id":"29","user_id":"19","title":"VIP Holiday Gift Guide (Email)","description":"One-day email marketing blast to our segmented VIP subscriber list. Features early access to sales.","kind":"Email Campaign","event_date":"2025-11-20","status":"0","status_message":"Scheduled","join_start":null,"join_end":null,"exposure_pre_start":null,"exposure_pre_end":null,"exposure_main_start":"2025-11-20","exposure_main_end":"2025-11-20","createdat":"2025-11-16 06:49:28","updatedat":"0000-00-00 00:00:00","join_start_ts":null,"join_end_ts":null,"exposure_pre_start_ts":null,"exposure_pre_end_ts":null,"exposure_main_start_ts":null,"exposure_main_end_ts":null},
{"id":"30","user_id":"6","title":"Q3 Financial Planning Webinar","description":"Completed service promotion. Drove sign-ups for a webinar via LinkedIn ads and email marketing.","kind":"Service Promotion","event_date":"2025-09-30","status":"2","status_message":"Campaign Completed","join_start":"2025-09-01","join_end":"2025-09-28","exposure_pre_start":"2025-09-01","exposure_pre_end":"2025-09-14","exposure_main_start":"2025-09-15","exposure_main_end":"2025-09-30","createdat":"2025-11-16 06:49:28","updatedat":"0000-00-00 00:00:00","join_start_ts":null,"join_end_ts":null,"exposure_pre_start_ts":null,"exposure_pre_end_ts":null,"exposure_main_start_ts":null,"exposure_main_end_ts":null},
{"id":"31","user_id":"12","title":"48-Hour Weekend Flash Sale","description":"Short, high-intensity campaign. 10 posts and constant stories over 48 hours. Ended today.","kind":"Product Promotion","event_date":"2025-11-16","status":"1","status_message":"Live - Final 4 hours","join_start":null,"join_end":null,"exposure_pre_start":"2025-11-14","exposure_pre_end":"2025-11-14","exposure_main_start":"2025-11-15","exposure_main_end":"2025-11-16","createdat":"2025-11-16 06:49:28","updatedat":"0000-00-00 00:00:00","join_start_ts":null,"join_end_ts":null,"exposure_pre_start_ts":null,"exposure_pre_end_ts":null,"exposure_main_start_ts":null,"exposure_main_end_ts":null},
{"id":"32","user_id":"15","title":"\"Taste of Winter\" Restaurant Menu","description":"Promoting the new seasonal menu. Heavy focus on high-quality food photography on Instagram.","kind":"Product Promotion","event_date":"2025-12-31","status":"0","status_message":"Pending - Photoshoot next week","join_start":null,"join_end":null,"exposure_pre_start":"2025-11-25","exposure_pre_end":"2025-11-30","exposure_main_start":"2025-12-01","exposure_main_end":"2025-12-31","createdat":"2025-11-16 06:49:28","updatedat":"0000-00-00 00:00:00","join_start_ts":null,"join_end_ts":null,"exposure_pre_start_ts":null,"exposure_pre_end_ts":null,"exposure_main_start_ts":null,"exposure_main_end_ts":null},
{"id":"33","user_id":"4","title":"Summer Vibe T-Shirt Contest (CANCELLED)","description":"This campaign was planned but cancelled due to production delays. All assets archived.","kind":"Giveaway","event_date":"2025-07-15","status":"3","status_message":"Cancelled - Production Delays","join_start":"2025-07-01","join_end":"2025-07-15","exposure_pre_start":"2025-06-25","exposure_pre_end":"2025-06-30","exposure_main_start":"2025-07-01","exposure_main_end":"2025-07-15","createdat":"2025-11-16 06:49:28","updatedat":"0000-00-00 00:00:00","join_start_ts":null,"join_end_ts":null,"exposure_pre_start_ts":null,"exposure_pre_end_ts":null,"exposure_main_start_ts":null,"exposure_main_end_ts":null},
{"id":"34","user_id":"17","title":"BizAnalytix SaaS Free Trial Drive","description":"Ongoing service promotion. LinkedIn and Twitter ad campaign targeting B2B managers. Goal: 500 trial sign-ups.","kind":"Service Promotion","event_date":"2025-11-30","status":"1","status_message":"Campaign Live - Monitoring CPA","join_start":"2025-11-01","join_end":"2025-11-30","exposure_pre_start":"2025-10-25","exposure_pre_end":"2025-10-31","exposure_main_start":"2025-11-01","exposure_main_end":"2025-11-30","createdat":"2025-11-16 06:49:28","updatedat":"0000-00-00 00:00:00","join_start_ts":null,"join_end_ts":null,"exposure_pre_start_ts":null,"exposure_pre_end_ts":null,"exposure_main_start_ts":null,"exposure_main_end_ts":null},
{"id":"35","user_id":"9","title":"Back to School Essentials Sale","description":"Completed campaign targeting parents and college students. Used promo code \"STUDY15\".","kind":"Product Promotion","event_date":"2025-09-05","status":"2","status_message":"Campaign Completed","join_start":null,"join_end":null,"exposure_pre_start":"2025-08-10","exposure_pre_end":"2025-08-14","exposure_main_start":"2025-08-15","exposure_main_end":"2025-09-05","createdat":"2025-11-16 06:49:28","updatedat":"0000-00-00 00:00:00","join_start_ts":null,"join_end_ts":null,"exposure_pre_start_ts":null,"exposure_pre_end_ts":null,"exposure_main_start_ts":null,"exposure_main_end_ts":null},
{"id":"36","user_id":"13","title":"Year-End Clearance Sale","description":"Goal: Liquidate Q4 stock. Heavy discount messaging. Planned for post-holiday lull.","kind":"Product Promotion","event_date":"2026-01-02","status":"0","status_message":"Pending","join_start":null,"join_end":null,"exposure_pre_start":"2025-12-20","exposure_pre_end":"2025-12-25","exposure_main_start":"2025-12-26","exposure_main_end":"2026-01-02","createdat":"2025-11-16 06:49:28","updatedat":"0000-00-00 00:00:00","join_start_ts":null,"join_end_ts":null,"exposure_pre_start_ts":null,"exposure_pre_end_ts":null,"exposure_main_start_ts":null,"exposure_main_end_ts":null},
{"id":"37","user_id":"18","title":"#MyAuraMoment TikTok Challenge","description":"User-generated content giveaway. Users post a video with our product and hashtag. Prize: $1,000.","kind":"Giveaway","event_date":"2025-12-01","status":"1","status_message":"Live - Accepting Submissions","join_start":"2025-11-10","join_end":"2025-12-01","exposure_pre_start":"2025-11-05","exposure_pre_end":"2025-11-09","exposure_main_start":"2025-11-10","exposure_main_end":"2025-12-01","createdat":"2025-11-16 06:49:28","updatedat":"0000-00-00 00:00:00","join_start_ts":null,"join_end_ts":null,"exposure_pre_start_ts":null,"exposure_pre_end_ts":null,"exposure_main_start_ts":null,"exposure_main_end_ts":null},
{"id":"38","user_id":"20","title":"Thanksgiving Food Bank Donation Match","description":"Charity promotion. For every order, we donated $1. Completed Nov 14. Raised $15,000.","kind":"Charity Promotion","event_date":"2025-11-14","status":"2","status_message":"Campaign Completed - Goal Met","join_start":null,"join_end":null,"exposure_pre_start":"2025-10-28","exposure_pre_end":"2025-10-31","exposure_main_start":"2025-11-01","exposure_main_end":"2025-11-14","createdat":"2025-11-16 06:49:28","updatedat":"0000-00-00 00:00:00","join_start_ts":null,"join_end_ts":null,"exposure_pre_start_ts":null,"exposure_pre_end_ts":null,"exposure_main_start_ts":null,"exposure_main_end_ts":null},
{"id":"39","user_id":"10","title":"Weekly Tech Tips Content Series","description":"Ongoing content marketing (not a sale). One new tip posted every Tuesday to build brand authority.","kind":"SNS Campaign","event_date":"2025-12-31","status":"1","status_message":"Live - Ongoing","join_start":null,"join_end":null,"exposure_pre_start":null,"exposure_pre_end":null,"exposure_main_start":"2025-10-01","exposure_main_end":"2025-12-31","createdat":"2025-11-16 06:49:28","updatedat":"0000-00-00 00:00:00","join_start_ts":null,"join_end_ts":null,"exposure_pre_start_ts":null,"exposure_pre_end_ts":null,"exposure_main_start_ts":null,"exposure_main_end_ts":null},
{"id":"40","user_id":"16","title":"Eco-Friendly Packaging Annoucement","description":"PR and brand-building campaign. 3 blog posts, 5 social posts, and 1 email explaining our new sustainable packaging.","kind":"Brand Promotion","event_date":"2025-11-05","status":"2","status_message":"Campaign Completed","join_start":null,"join_end":null,"exposure_pre_start":null,"exposure_pre_end":null,"exposure_main_start":"2025-11-01","exposure_main_end":"2025-11-05","createdat":"2025-11-16 06:49:28","updatedat":"0000-00-00 00:00:00","join_start_ts":null,"join_end_ts":null,"exposure_pre_start_ts":null,"exposure_pre_end_ts":null,"exposure_main_start_ts":null,"exposure_main_end_ts":null},
{"id":"41","user_id":null,"title":"A promo on energy drink","description":"Fuel Your Flow","kind":"PROMO","event_date":null,"status":"0","status_message":null,"join_start":null,"join_end":null,"exposure_pre_start":null,"exposure_pre_end":null,"exposure_main_start":null,"exposure_main_end":null,"createdat":"2025-11-16 15:24:01","updatedat":null,"join_start_ts":null,"join_end_ts":null,"exposure_pre_start_ts":null,"exposure_pre_end_ts":null,"exposure_main_start_ts":null,"exposure_main_end_ts":null}
]
}
]
